[
    {
        "title": "ffrferf loremLorem Ipsum is simply dummy text of the printing and typesetting industry. Lorem Ipsum has been the industry's standard dummy text ever since the 1500s, when an unknown printer took a galley of type and scrambled it to make a type specimen book. It has survived not only five centuries, but also the leap into electronic typesetting, remaining essentially unchanged. It was popularised in the 1960s with the release of Letraset sheets containing L ",
        "shortDesc": "ferfeferf ffrferf Lorem Ipsum is simply dummy text of the printing and typesetting industry. Lorem Ipsum has been the industry's standard",
        "shortLink": "fwefwefwef",
        "hastags": "",
        "categories": [
            "Последние новости",
            "Мир",
            "Экономика"
        ],
        "slug": "fwefwefwef",
        "img": "/uploads/16776022455343news.jpg",
        "date": "2023-02-28T16:37:25.536Z"
    },
    {
        "title": "ffrferf Lorem Ipsum is simply dummy text of the printing and typesetting industry. Lorem Ipsum has been the industry's standard dummy text ever since the 1500s, when an unknown printer took a galley of type and scrambled it to make a type specimen book. It has survived not only five centuries, but also the leap into electronic typesetting, remaining essentially unchanged. It was popularised in the 1960s with the release of Letraset sheets containing L",
        "shortDesc": "ferfeferf",
        "shortLink": "fwefwefwef",
        "hastags": "",
        "categories": [
            "Последние новости",
            "Мир",
            "Экономика"
        ],
        "slug": "fwefwefwef",
        "img": "/uploads/16776030397013news.jpg",
        "date": "2023-02-28T16:50:39.704Z"
    },
    {
        "title": "Lorem Ipsum is simply dummy text of the printing and typesetting industry. Lorem Ipsum has been the industry's standard dummy text ever since the 1500s, when an unknown printer took a galley of type and scrambled it to make a type specimen book. It has survived not only five centuries, but also the leap into electronic typesetting, remaining essentially unchanged. It was popularised in the 1960s with the release of Letraset sheets containing L",
        "shortDesc": "ferfeferf",
        "shortLink": "fwefwefwef",
        "hastags": "",
        "categories": [
            "Последние новости",
            "Мир",
            "Экономика"
        ],
        "slug": "fwefwefwef Lorem Ipsum is simply dummy text of the printing and typesetting industry. Lorem Ipsum has been the industry's standard dummy text ever since the 1500s, when an unknown printer took a galley of type and scrambled it to make a type specimen book. It has survived not only five centuries, but also the leap into electronic typesetting, remaining essentially unchanged. It was popularised in the 1960s with the release of Letraset sheets containing L",
        "img": "/uploads/16776030439343news.jpg",
        "date": "2023-02-28T16:50:43.935Z"
    },
    {
        "title": "ffrferf Lorem Ipsum is simply dummy text of the printing and typesetting industry. Lorem Ipsum has been the industry's standard dummy text ever since the 1500s, when an unknown printer took a galley of type and scrambled it to make a type specimen book. It has survived not only five centuries, but also the leap into electronic typesetting, remaining essentially unchanged. It was popularised in the 1960s with the release of Letraset sheets containing L",
        "shortDesc": "ferfeferf",
        "shortLink": "fwefwefwef",
        "hastags": "",
        "categories": [
            "Последние новости",
            "Мир",
            "Экономика"
        ],
        "slug": "fwefwefwef",
        "img": "/uploads/16776030479853news.jpg",
        "date": "2023-02-28T16:50:47.990Z"
    },
    {
        "title": "ffrferf",
        "shortDesc": "ferfeferf",
        "shortLink": "fwefwefwef",
        "hastags": "",
        "categories": [
            "Последние новости",
            "Мир",
            "Экономика"
        ],
        "slug": "fwefwefwef",
        "img": "/uploads/16776030511783news.jpg",
        "date": "2023-02-28T16:50:51.179Z"
    },
    {
        "title": "ffrferf",
        "shortDesc": "ferfeferf",
        "shortLink": "fwefwefwef",
        "hastags": "",
        "categories": [
            "Последние новости",
            "Мир",
            "Экономика"
        ],
        "slug": "fwefwefwef",
        "img": "/uploads/16776038029733news.jpg",
        "date": "2023-02-28T17:03:22.985Z"
    },
    {
        "title": "ffrferf",
        "shortDesc": "ferfeferf",
        "shortLink": "fwefwefwef",
        "hastags": "",
        "categories": [
            "Последние новости",
            "Мир",
            "Экономика"
        ],
        "slug": "fwefwefwef",
        "img": "/uploads/16776043563383news.jpg",
        "date": "2023-02-28T17:12:36.340Z"
    },
    {
        "title": "ffrferf",
        "shortDesc": "ferfeferf",
        "shortLink": "fwefwefwef",
        "hastags": "",
        "slug": "fwefwefwef",
        "img": "/uploads/16776044464774news.jpg",
        "date": "2023-02-28T17:14:06.483Z"
    },
    {
        "title": "ffrferf",
        "shortDesc": "ferfeferf",
        "shortLink": "fwefwefwef",
        "hastags": "",
        "slug": "fwefwefwef",
        "img": "/uploads/16776044768091news.jpg",
        "date": "2023-02-28T17:14:36.813Z"
    },
    {
        "title": "ffrferf",
        "shortDesc": "ferfeferf",
        "shortLink": "fwefwefwef",
        "hastags": "",
        "categories": [
            "Последние новости",
            "Мир",
            "Экономика"
        ],
        "slug": "fwefwefwef",
        "img": "/uploads/16776047545921news.jpg",
        "date": "2023-02-28T17:19:14.595Z"
    },
    {
        "title": "erwferff",
        "shortDesc": "erfwerferff",
        "shortLink": "ewrfwerf",
        "hastags": "",
        "slug": "ewrfwerf",
        "img": "/uploads/1677605222862pexels-photo-112460.jpeg",
        "date": "2023-02-28T17:27:02.867Z"
    },
    {
        "title": "erwferff",
        "shortDesc": "erfwerferff",
        "shortLink": "ewrfwerf",
        "hastags": "",
        "slug": "ewrfwerf",
        "img": "/uploads/1677605410462pexels-photo-112460.jpeg",
        "date": "2023-02-28T17:30:10.467Z"
    },
    {
        "title": "erwferff",
        "shortDesc": "erfwerferff",
        "shortLink": "ewrfwerf",
        "hastags": "",
        "slug": "ewrfwerf",
        "img": "/uploads/1677605518230pexels-photo-112460.jpeg",
        "date": "2023-02-28T17:31:58.234Z"
    },
    {
        "title": "erwferff",
        "shortDesc": "erfwerferff",
        "shortLink": "ewrfwerf",
        "hastags": "",
        "slug": "ewrfwerf",
        "img": "/uploads/1677605669288pexels-photo-112460.jpeg",
        "date": "2023-02-28T17:34:29.292Z"
    }
]